venvpool/__init__.py
venvpool/motivate.py
venvpool/tempvenv.py
venvpool/util.py
venvpool-22.dist-info/METADATA
venvpool-22.dist-info/WHEEL
venvpool-22.dist-info/entry_points.txt
venvpool-22.dist-info/top_level.txt
venvpool-22.dist-info/RECORD
