Metadata-Version: 2.1
Name: venvpool
Version: 22
Summary: Run your Python scripts using an automated pool of virtual environments to satisfy their requirements
Home-page: https://pypi.org/project/venvpool/
Author: foyono
Author-email: shrovis@foyono.com
